pvconnect/__init__.py
pvconnect/cli.py
pvconnect/connection.py
paraview_connect-1.0.1.dist-info/LICENSE
paraview_connect-1.0.1.dist-info/METADATA
paraview_connect-1.0.1.dist-info/WHEEL
paraview_connect-1.0.1.dist-info/entry_points.txt
paraview_connect-1.0.1.dist-info/top_level.txt
paraview_connect-1.0.1.dist-info/RECORD
