Metadata-Version: 2.1
Name: paraview-connect
Version: 1.0.1
Summary: "Helper tool and library for connecting to remote Paraview sessions"
Home-page: https://github.com/zenotech/ParaViewConnect/
Author: "Zenotech"
Author-email: "support@zenotech.com"
License: BSD 3-Clause License
Classifier: License :: OSI Approved :: BSD License
Classifier: Programming Language :: Python :: 3
Classifier: Programming Language :: Python :: 3.5
Classifier: Programming Language :: Python :: 3.6
Classifier: Programming Language :: Python :: 3.7
License-File: LICENSE
Requires-Dist: fabric (>=2.6.0)
Requires-Dist: click (>=7.1.2)
